wallet_tracking/__init__.py
wallet_tracking/tracker.py
wallet_tracking-1.0.3.dist-info/METADATA
wallet_tracking-1.0.3.dist-info/WHEEL
wallet_tracking-1.0.3.dist-info/top_level.txt
wallet_tracking-1.0.3.dist-info/zip-safe
wallet_tracking-1.0.3.dist-info/RECORD
