Metadata-Version: 2.4
Name: wallet-tracking
Version: 1.0.3
Summary: copy trading bot tracking
Home-page: 
Author: Private
Author-email: 
Classifier: Development Status :: 4 - Beta
Classifier: Intended Audience :: Developers
Classifier: Programming Language :: Python :: 3
Requires-Python: >=3.8
Requires-Dist: requests>=2.28.0
Dynamic: author
Dynamic: classifier
Dynamic: description
Dynamic: description-content-type
Dynamic: requires-dist
Dynamic: requires-python
Dynamic: summary
